{
  "slug": "Barrel",
  "equipment": {
    "category": "Usable Equipment",
    "medal": "Bristias Guardian Justice and Glory",
    "head": "Justice Glorieux Liberte hair",
    "earring": "Earring",
    "face": "None",
    "accessory": "Accessory",
    "necklace": "Necklace",
    "back": "All Characters",
    "armor": "Coat",
    "costume": "Justice Glorieux Liberte",
    "gloves": "Gloves Leather",
    "ring": "Ring",
    "weapon_costume": "Bristian Miracle Bristian Miracle (Event)",
    "belt": "Belt Leather",
    "shoes": "Shoes Leather",
    "artifact": "Barrels Keg Dom Perignon",
    "runestone": "Runestone",
    "pet_spirit": "Pet Spirit"
  },
  "character_buff": {
    "name": "Drunken",
    "image": "job_drunken.jpg",
    "description": "Whenever you drink, buff level increases and can get to max 15 level, but various side effect could follow. Skill damage 1.5~2 times",
    "target": "Self-buff",
    "casting_time": "0 sec.",
    "cooldown": "20 sec.",
    "duration": "2.366 sec.",
    "sp_cost": "200",
    "consume_item": "Ancient Star Orb × 3",
    "levels": [
      {
        "level": "Level 1",
        "effects": [
          "Duration : 90 secs.",
          "Damage +2%",
          "Critical Rate +1%",
          "Movement Speed +1%"
        ]
      },
      {
        "level": "Level 10",
        "effects": [
          "Duration : 90 secs.",
          "Damage +20%",
          "Critical Rate +10%",
          "Movement Speed +10%"
        ]
      },
      {
        "level": "Level 11",
        "effects": [
          "Duration : 90 secs.",
          "Damage +22%",
          "Critical Rate +11%",
          "Movement Speed +11%",
          "A.R. +1"
        ]
      },
      {
        "level": "Level 12",
        "effects": [
          "Duration : 90 secs.",
          "Damage +24%",
          "Critical Rate +12%",
          "Movement Speed +12%",
          "A.R. +1"
        ]
      },
      {
        "level": "Level 13",
        "effects": [
          "Duration : 90 secs.",
          "Damage +26%",
          "Critical Rate +13%",
          "Movement Speed +13%",
          "A.R. +1"
        ]
      }
    ]
  },
  "stance_overview": [
    {
      "stance_name": "Bare Knuckle",
      "equipped_items": "None",
      "icon_position": {
        "x": -150,
        "y": 0
      }
    },
    {
      "stance_name": "Freestyle Shot",
      "equipped_items": "Pistol",
      "icon_position": {
        "x": -150,
        "y": -50
      }
    },
    {
      "stance_name": "Double-Gun Shot",
      "equipped_items": "Pistol + Pistol",
      "icon_position": {
        "x": 0,
        "y": -25
      }
    },
    {
      "stance_name": "Outrage Shot",
      "equipped_items": "Pistol + Pistol",
      "icon_position": {
        "x": -100,
        "y": -375
      }
    },
    {
      "stance_name": "Cobra",
      "equipped_items": "Pistol + Pistol",
      "icon_position": {
        "x": -350,
        "y": -175
      }
    }
  ],
  "stances": [
    {
      "name": "Bare Knuckle",
      "info": {
        "Targets": "1 enemy",
        "Range": "1m away",
        "Splash": "None",
        "Hits per attack": "2",
        "Hits flying": "No",
        "Flying": "No",
        "Regenerate SP": "Yes"
      },
      "stats": {
        "ASPD": "167",
        "Bonus ATK": "0%",
        "MSPD": "1",
        "MSPD Limit": "8.50",
        "ACC": "100",
        "EVA": "0",
        "BLK": "0",
        "Fire RES": "0",
        "Ice RES": "0",
        "Lightning RES": "0",
        "Abnormal RES": "0"
      },
      "lv25_bonus": {},
      "consume": "",
      "skills": [],
      "lv25_bonus_extra": [
        "None"
      ],
      "equipped_items": "None",
      "icon_position": {
        "x": -150,
        "y": 0
      }
    },
    {
      "name": "Freestyle Shot",
      "info": {
        "Targets": "1 enemy",
        "Range": "0.5~9m away",
        "Splash": "None",
        "Hits per attack": "1",
        "Hits flying": "Yes",
        "Flying": "No",
        "Regenerate SP": "Yes"
      },
      "stats": {
        "ASPD": "130",
        "Bonus ATK": "200%",
        "MSPD": "1",
        "MSPD Limit": "8.00",
        "ACC": "20",
        "EVA": "5",
        "BLK": "0",
        "Fire RES": "0",
        "Ice RES": "0",
        "Lightning RES": "0",
        "Abnormal RES": "0"
      },
      "lv25_bonus": {
        "ATK SPD": "+16%",
        "Ignore DEF": "+2%",
        "Evasion": "+5",
        "Critical": "+6"
      },
      "consume": "",
      "skills": [
        {
          "name": "Westraid",
          "image": "fre_westraid.jpg",
          "description": "Increases your shooting speed but sacrifices accuracy. A change of stance will cause you to lose this effect.",
          "target": "",
          "casting_time": "1.133 sec.",
          "cooldown": "0 sec.",
          "duration": "1.13 sec.",
          "hits_flying": "Yes",
          "knock_down": "No",
          "sp_cost": "150",
          "aggro": "0",
          "skill_type": "Buff",
          "consume_item": "",
          "soft_armor_atk": "",
          "heavy_armor_atk": "",
          "light_armor_atk": "",
          "levels": [
            {
              "level": "Level 1",
              "value": "",
              "effects": [
                "Duration : 33 sec",
                "ATK SPD +8%",
                "Accuracy -38"
              ]
            },
            {
              "level": "Level 10",
              "value": "",
              "effects": [
                "Duration : 60 sec",
                "ATK SPD +16%",
                "Accuracy -25"
              ]
            },
            {
              "level": "Level 11",
              "value": "",
              "effects": [
                "Duration : 63 sec",
                "ATK SPD +16%",
                "Accuracy -23",
                "A.R. +1"
              ]
            },
            {
              "level": "Level 12",
              "value": "",
              "effects": [
                "Duration : 66 sec",
                "ATK SPD +17%",
                "Accuracy -22",
                "A.R. +1"
              ]
            },
            {
              "level": "Level 13",
              "value": "",
              "effects": [
                "Duration : 69 sec",
                "ATK SPD +18%",
                "Accuracy -20",
                "A.R. +1"
              ]
            }
          ],
          "special": []
        },
        {
          "name": "Triple Firing",
          "image": "fre_triplefiring.jpg",
          "description": "A rapid attack of 3 shots.",
          "target": "1 enemy within a range of 9m",
          "casting_time": "1 sec.",
          "cooldown": "7 sec.",
          "duration": "1.3 sec.",
          "hits_flying": "Yes",
          "knock_down": "No",
          "sp_cost": "200",
          "aggro": "72",
          "skill_type": "Shooting",
          "consume_item": "",
          "soft_armor_atk": "",
          "heavy_armor_atk": "",
          "light_armor_atk": "",
          "levels": [
            {
              "level": "Level 1",
              "value": "АТК: 308%",
              "effects": []
            },
            {
              "level": "Level 10",
              "value": "АТК: 616%",
              "effects": []
            }
          ],
          "special": []
        },
        {
          "name": "Quick and Dead",
          "image": "fre_quickanddead.jpg",
          "description": "Fires randomly at a group of enemies.",
          "target": "Up to 5 enemies 9m away and within a 3m radius",
          "casting_time": "1 sec.",
          "cooldown": "14 sec.",
          "duration": "3.73 sec.",
          "hits_flying": "Yes",
          "knock_down": "No",
          "sp_cost": "300",
          "aggro": "88",
          "skill_type": "Shooting",
          "consume_item": "",
          "soft_armor_atk": "",
          "heavy_armor_atk": "",
          "light_armor_atk": "",
          "levels": [
            {
              "level": "Level 1",
              "value": "АТК: 391%",
              "effects": []
            },
            {
              "level": "Level 10",
              "value": "АТК: 782%",
              "effects": []
            }
          ],
          "special": []
        }
      ],
      "equipped_items": "Pistol",
      "icon_position": {
        "x": -150,
        "y": -50
      }
    },
    {
      "name": "Double-Gun Shot",
      "info": {
        "Targets": "1 enemy",
        "Range": "0.5~9m away",
        "Splash": "None",
        "Hits per attack": "2",
        "Hits flying": "Yes",
        "Flying": "No",
        "Regenerate SP": "Yes"
      },
      "stats": {
        "ASPD": "200",
        "Bonus ATK": "200%",
        "MSPD": "1",
        "MSPD Limit": "8.00",
        "ACC": "0",
        "EVA": "5",
        "BLK": "0",
        "Fire RES": "0",
        "Ice RES": "0",
        "Lightning RES": "0",
        "Abnormal RES": "0"
      },
      "lv25_bonus": {
        "ATK SPD": "+20%",
        "Ignore DEF": "+2%",
        "Evasion": "+5"
      },
      "consume": "",
      "skills": [
        {
          "name": "Westraid",
          "image": "fre_westraid.jpg",
          "description": "Increases your shooting speed but sacrifices accuracy. A change of stance will cause you to lose this effect.",
          "target": "",
          "casting_time": "1.133 sec.",
          "cooldown": "0 sec.",
          "duration": "1.13 sec.",
          "hits_flying": "Yes",
          "knock_down": "No",
          "sp_cost": "150",
          "aggro": "0",
          "skill_type": "Buff",
          "consume_item": "",
          "soft_armor_atk": "",
          "heavy_armor_atk": "",
          "light_armor_atk": "",
          "levels": [
            {
              "level": "Level 1",
              "value": "",
              "effects": [
                "Duration : 33 sec",
                "ATK SPD +8%",
                "Accuracy -38"
              ]
            },
            {
              "level": "Level 10",
              "value": "",
              "effects": [
                "Duration : 60 sec",
                "ATK SPD +16%",
                "Accuracy -25"
              ]
            },
            {
              "level": "Level 11",
              "value": "",
              "effects": [
                "Duration : 63 sec",
                "ATK SPD +16%",
                "Accuracy -23",
                "A.R. +1"
              ]
            },
            {
              "level": "Level 12",
              "value": "",
              "effects": [
                "Duration : 66 sec",
                "ATK SPD +17%",
                "Accuracy -22",
                "A.R. +1"
              ]
            },
            {
              "level": "Level 13",
              "value": "",
              "effects": [
                "Duration : 69 sec",
                "ATK SPD +18%",
                "Accuracy -20",
                "A.R. +1"
              ]
            }
          ],
          "special": []
        },
        {
          "name": "Bloody Overdrive",
          "image": "dgs_bloodyoverdrive.jpg",
          "description": "Fires mercilessly in all directions at surrounding enemies.",
          "target": "Up to 8 enemies within a range of 7.5m",
          "casting_time": "1.6 sec.",
          "cooldown": "10 sec.",
          "duration": "3.57 sec.",
          "hits_flying": "Yes",
          "knock_down": "No",
          "sp_cost": "200",
          "aggro": "59",
          "skill_type": "Shooting",
          "consume_item": "",
          "soft_armor_atk": "",
          "heavy_armor_atk": "",
          "light_armor_atk": "",
          "levels": [
            {
              "level": "Level 1",
              "value": "АТК: 234%",
              "effects": []
            },
            {
              "level": "Level 10",
              "value": "АТК: 468%",
              "effects": []
            }
          ],
          "special": []
        },
        {
          "name": "Quattro Firing",
          "image": "dgs_quattrofiring.jpg",
          "description": "Fires 4 rapid shots at a single enemy.",
          "target": "1 enemy within a range of 9m",
          "casting_time": "1.033 sec.",
          "cooldown": "15 sec.",
          "duration": "2.07 sec.",
          "hits_flying": "Yes",
          "knock_down": "No",
          "sp_cost": "250",
          "aggro": "131",
          "skill_type": "Shooting",
          "consume_item": "",
          "soft_armor_atk": "",
          "heavy_armor_atk": "",
          "light_armor_atk": "",
          "levels": [
            {
              "level": "Level 1",
              "value": "АТК: 596%",
              "effects": []
            },
            {
              "level": "Level 10",
              "value": "АТК: 1192%",
              "effects": []
            }
          ],
          "special": []
        },
        {
          "name": "R.I.P.",
          "image": "dgs_restinpeace.jpg",
          "description": "Fires a series of rapid shots at an enemy with dual pistols.",
          "target": "1 enemy within a range of 9m",
          "casting_time": "1 sec.",
          "cooldown": "20 sec.",
          "duration": "3.53 sec.",
          "hits_flying": "Yes",
          "knock_down": "No",
          "sp_cost": "300",
          "aggro": "201",
          "skill_type": "Shooting",
          "consume_item": "",
          "soft_armor_atk": "",
          "heavy_armor_atk": "",
          "light_armor_atk": "",
          "levels": [
            {
              "level": "Level 1",
              "value": "АТК: 946%",
              "effects": []
            },
            {
              "level": "Level 10",
              "value": "АТК: 1892%",
              "effects": []
            }
          ],
          "special": []
        }
      ],
      "equipped_items": "Pistol + Pistol",
      "icon_position": {
        "x": 0,
        "y": -25
      }
    },
    {
      "name": "Outrage Shot",
      "info": {
        "Targets": "1 enemy",
        "Range": "0.5~9m away",
        "Splash": "None",
        "Hits per attack": "4",
        "Hits flying": "Yes",
        "Flying": "No",
        "Regenerate SP": "Yes"
      },
      "stats": {
        "ASPD": "213",
        "Bonus ATK": "200%",
        "MSPD": "1",
        "MSPD Limit": "8.00",
        "ACC": "0",
        "EVA": "0",
        "BLK": "0",
        "Fire RES": "0",
        "Ice RES": "0",
        "Lightning RES": "0",
        "Abnormal RES": "0"
      },
      "lv25_bonus": {
        "ATK SPD": "+25%",
        "Ignore DEF": "+2%"
      },
      "consume": "",
      "skills": [
        {
          "name": "Sapping Shots",
          "image": "ors_sappingshot.jpg",
          "description": "Fires at enemy (Unable to move the lower half of own body).",
          "target": "1 enemy within a range of 6m",
          "casting_time": "Instant",
          "cooldown": "10 sec.",
          "duration": "2.37 sec.",
          "hits_flying": "Yes",
          "knock_down": "Yes",
          "sp_cost": "100",
          "aggro": "114",
          "skill_type": "Shooting",
          "consume_item": "",
          "soft_armor_atk": "",
          "heavy_armor_atk": "",
          "light_armor_atk": "",
          "levels": [
            {
              "level": "Level 1",
              "value": "АТК: 525%",
              "effects": [
                "25% chance to inflict [Mortal Wound]"
              ]
            },
            {
              "level": "Level 10",
              "value": "АТК: 1050%",
              "effects": [
                "25% chance to inflict [Mortal Wound]"
              ]
            }
          ],
          "special": []
        },
        {
          "name": "Octet-stream",
          "image": "ors_octetstream.jpg",
          "description": "Fires 8 times consecutively.",
          "target": "1 enemy within a range of 7m.",
          "casting_time": "1.033 sec.",
          "cooldown": "10 sec.",
          "duration": "2.53 sec.",
          "hits_flying": "Yes",
          "knock_down": "No",
          "sp_cost": "200",
          "aggro": "236",
          "skill_type": "Shooting",
          "consume_item": "",
          "soft_armor_atk": "",
          "heavy_armor_atk": "",
          "light_armor_atk": "",
          "levels": [
            {
              "level": "Level 1",
              "value": "АТК: 1132%",
              "effects": []
            },
            {
              "level": "Level 10",
              "value": "АТК: 2264%",
              "effects": []
            }
          ],
          "special": []
        },
        {
          "name": "Dancing Revolvers",
          "image": "ors_dancingrevolver.jpg",
          "description": "A frenzy of graceful shots at enemies.",
          "target": "Up to 6 enemies 8m away and within a 4m radius.",
          "casting_time": "1.367 sec.",
          "cooldown": "15 sec.",
          "duration": "3.67 sec.",
          "hits_flying": "Yes",
          "knock_down": "No",
          "sp_cost": "250",
          "aggro": "144",
          "skill_type": "Shooting",
          "consume_item": "",
          "soft_armor_atk": "",
          "heavy_armor_atk": "",
          "light_armor_atk": "",
          "levels": [
            {
              "level": "Level 1",
              "value": "АТК: 673%",
              "effects": [
                "50% chance to inflict [Mortal Wound] on enemy"
              ]
            },
            {
              "level": "Level 10",
              "value": "АТК: 1346%",
              "effects": [
                "50% chance to inflict [Mortal Wound] on enemy"
              ]
            }
          ],
          "special": []
        },
        {
          "name": "Desperados",
          "image": "ors_desperados.jpg",
          "description": "Random shots at enemies.",
          "target": "1 enemy within a range of 9m",
          "casting_time": "1.533 sec.",
          "cooldown": "20 sec.",
          "duration": "5.53 sec.",
          "hits_flying": "Yes",
          "knock_down": "No",
          "sp_cost": "300",
          "aggro": "241",
          "skill_type": "Shooting",
          "consume_item": "",
          "soft_armor_atk": "",
          "heavy_armor_atk": "",
          "light_armor_atk": "",
          "levels": [
            {
              "level": "Level 1",
              "value": "АТК: 1152%",
              "effects": [
                "Enemy DEF -50",
                "100% chance to inflict [Mortal Wound] on enemy"
              ]
            },
            {
              "level": "Level 10",
              "value": "АТК: 2304%",
              "effects": [
                "Enemy DEF -50",
                "100% chance to inflict [Mortal Wound] on enemy"
              ]
            }
          ],
          "special": []
        }
      ],
      "equipped_items": "Pistol + Pistol",
      "icon_position": {
        "x": -100,
        "y": -375
      }
    },
    {
      "name": "Cobra",
      "info": {
        "Targets": "1 enemy",
        "Range": "0.1~9m away",
        "Splash": "None",
        "Hits per attack": "4",
        "Hits flying": "Yes",
        "Flying": "No",
        "Regenerate SP": "Yes",
        "Magical DMG": "-20%"
      },
      "stats": {
        "ASPD": "213",
        "Bonus ATK": "300%",
        "MSPD": "1",
        "MSPD Limit": "8.00",
        "ACC": "0",
        "EVA": "0",
        "BLK": "0",
        "Fire RES": "0",
        "Ice RES": "0",
        "Lightning RES": "0",
        "Abnormal RES": "0"
      },
      "lv25_bonus": {
        "ATK SPD": "+13%",
        "Ignore DEF": "+7%",
        "Critical": "+10",
        "Penetration": "10+15",
        "Immunity": "5"
      },
      "consume": "Large Caliber Bullet x 4",
      "skills": [
        {
          "name": "Back Rolling Fire",
          "image": "cbr_backrollingfire.jpg",
          "description": "After tumbling backwards, assumes sitting position and shoots.",
          "target": "Up to 5 enemies 9m away and within 5m radius",
          "casting_time": "1.2 sec.",
          "cooldown": "12 sec.",
          "duration": "3.5 sec.",
          "hits_flying": "Yes",
          "knock_down": "Yes",
          "sp_cost": "250",
          "aggro": "172",
          "skill_type": "Shooting",
          "consume_item": "Large Caliber Bullet x 9",
          "soft_armor_atk": "",
          "heavy_armor_atk": "120%",
          "light_armor_atk": "110%",
          "levels": [
            {
              "level": "Level 1",
              "value": "АТК: 1000%",
              "effects": [
                "Ignores enemy DEF by 40",
                "Deals [Burn] with 50% chance",
                "[Drunken] state, 1.5~2 times damage"
              ]
            },
            {
              "level": "Level 10",
              "value": "АТК: 2000%",
              "effects": [
                "Ignores enemy DEF by 40",
                "Deals [Burn] with 50% chance",
                "[Drunken] state, 1.5~2 times damage"
              ]
            }
          ],
          "special": []
        },
        {
          "name": "Shooting Canon",
          "image": "cbr_shootingcannon.jpg",
          "description": "As tumbling forward, shoots with two guns ruthlessly.",
          "target": "",
          "casting_time": "1.133 sec.",
          "cooldown": "15 sec.",
          "duration": "4.3 sec.",
          "hits_flying": "Yes",
          "knock_down": "Yes",
          "sp_cost": "350",
          "aggro": "210",
          "skill_type": "Shooting",
          "consume_item": "Large Caliber Bullet x 14",
          "soft_armor_atk": "",
          "heavy_armor_atk": "110%",
          "light_armor_atk": "110%",
          "levels": [
            {
              "level": "Level 1",
              "value": "АТК: 1100%",
              "effects": [
                "Ignores enemy DEF by 50",
                "Add. damage if target in under [Burn], [Burning Wave] or [Scald]",
                "[Drunken] state, 1.5~2 times damage."
              ]
            },
            {
              "level": "Level 10",
              "value": "АТК: 2200%",
              "effects": [
                "Ignores enemy DEF by 50",
                "Add. damage if target in under [Burn], [Burning Wave] or [Scald]",
                "[Drunken] state, 1.5~2 times damage."
              ]
            }
          ],
          "special": []
        },
        {
          "name": "Heavy Drinker",
          "image": "cbr_drinkingparty.jpg",
          "description": "Randomly debuffs targets by making them drink and becomes [Drunken] status. Debuff chance decreases for Boss Grade Monsters.",
          "target": "",
          "casting_time": "Instant",
          "cooldown": "90 sec.",
          "duration": "2.366 sec.",
          "hits_flying": "Yes",
          "knock_down": "No",
          "sp_cost": "400",
          "aggro": "0",
          "skill_type": "Buff",
          "consume_item": "Ancient Star Orb x 10",
          "soft_armor_atk": "",
          "heavy_armor_atk": "",
          "light_armor_atk": "",
          "levels": [
            {
              "level": "Level 1",
              "value": "",
              "effects": [
                "80% chance to inflict [Random Debuff] Lv.1 on enemy",
                "Ignores Debuff RES of enemy",
                "[Drunken] buff to yourself"
              ]
            },
            {
              "level": "Level 10",
              "value": "",
              "effects": [
                "80% chance to inflict [Random Debuff] Lv.10 on enemy",
                "Ignores Debuff RES of enemy",
                "[Drunken] buff to yourself"
              ]
            },
            {
              "level": "Level 11",
              "value": "",
              "effects": [
                "80% chance to inflict [Random Debuff] Lv.11 on enemy",
                "Ignores Debuff RES of enemy",
                "[Drunken] buff to yourself"
              ]
            },
            {
              "level": "Level 12",
              "value": "",
              "effects": [
                "80% chance to inflict [Random Debuff] Lv.12 on enemy",
                "Ignores Debuff RES of enemy",
                "[Drunken] buff to yourself"
              ]
            },
            {
              "level": "Level 13",
              "value": "",
              "effects": [
                "80% chance to inflict [Random Debuff] Lv.13 on enemy",
                "Ignores Debuff RES of enemy",
                "[Drunken] buff to yourself"
              ]
            }
          ],
          "special": []
        },
        {
          "name": "Breaking Storm",
          "image": "cbr_breakingstorm.jpg",
          "description": "Spins like a top while lying down and fires ruthlessly.",
          "target": "Up to 10 enemies 8m away.",
          "casting_time": "1.1 sec.",
          "cooldown": "18 sec.",
          "duration": "5.367 sec.",
          "hits_flying": "Yes",
          "knock_down": "Yes",
          "sp_cost": "400",
          "aggro": "90",
          "skill_type": "Shooting",
          "consume_item": "Large Caliber Bullet x 16",
          "soft_armor_atk": "80%",
          "heavy_armor_atk": "110%",
          "light_armor_atk": "",
          "levels": [
            {
              "level": "Level 1",
              "value": "АТК: 850%",
              "effects": [
                "Ignores enemy DEF by 50",
                "[Drunken] state, 1.5~2 times damage"
              ]
            },
            {
              "level": "Level 10",
              "value": "АТК: 1700%",
              "effects": [
                "Ignores enemy DEF by 50",
                "[Drunken] state, 1.5~2 times damage"
              ]
            }
          ],
          "special": []
        },
        {
          "name": "Endless Waltz",
          "image": "cbr_endlesswaltz.jpg",
          "description": "Shoots tons of bullets while stepping back slowly.",
          "target": "1 enemy within a range of 12m",
          "casting_time": "Instant",
          "cooldown": "20 sec.",
          "duration": "4.333 sec.",
          "hits_flying": "Yes",
          "knock_down": "Yes",
          "sp_cost": "450",
          "aggro": "490",
          "skill_type": "Shooting",
          "consume_item": "Large Caliber Bullet x 18",
          "soft_armor_atk": "",
          "heavy_armor_atk": "110%",
          "light_armor_atk": "125%",
          "levels": [
            {
              "level": "Level 1",
              "value": "АТК: 2580%",
              "effects": [
                "Ignores enemy DEF by 75",
                "Ignore Blocking",
                "Deals [Burn] with 50% chance",
                "[Drunken] state, 1.5~2 times damage"
              ]
            },
            {
              "level": "Level 10",
              "value": "АТК: 5160%",
              "effects": [
                "Ignores enemy DEF by 75",
                "Ignore Blocking",
                "Deals [Burn] with 50% chance",
                "[Drunken] state, 1.5~2 times damage"
              ]
            }
          ],
          "special": []
        }
      ],
      "lv25_bonus_extra": [
        "[RE: PvE] Skill DMG increases equal to 8% of extra [DEX]",
        "[PVP/PVE Maps] Additional 5% DMG according to extra [DEX]",
        "Ignore additional DEF according to extra [DEX] * 4",
        "Additional DMG against [PC] + 1x",
        "Additional DMG against Monster according to 5 * 50"
      ],
      "equipped_items": "Pistol + Pistol",
      "icon_position": {
        "x": -350,
        "y": -175
      }
    }
  ]
}