{
  "slug": "Heyran2",
  "equipment": {
    "category": "Usable Equipment",
    "medal": "Avengers from Bristia",
    "head": "None",
    "earring": "Earring",
    "face": "None",
    "accessory": "Accessory",
    "necklace": "Necklace",
    "back": "All Characters",
    "armor": "Leather",
    "costume": "None",
    "gloves": "Gloves Leather",
    "ring": "Ring",
    "weapon_costume": "Bloody Rose Dagger Bloody Rose Dagger (Event)",
    "belt": "Belt Leather",
    "shoes": "Shoes Leather",
    "artifact": "Bloody Hair Ribbon Leather Sheath",
    "runestone": "Runestone",
    "pet_spirit": "Pet Spirit"
  },
  "character_buff": {
    "name": "Dagger Polish",
    "image": "job_daggerpolish2.jpg",
    "description": "With a sharpened blade, every normal attack hit inflicts mortal wounds. HP of enemies with active [Enhanced Pierced Wound] decreases gradually in proportion to damage. 1/5 applies to PC.",
    "target": "Self-buff",
    "casting_time": "0 sec.",
    "cooldown": "0 sec.",
    "duration": "1.03 sec.",
    "sp_cost": "100",
    "consume_item": "Ancient Star Orb × 2",
    "levels": [
      {
        "level": "Level 1",
        "effects": [
          "Duration 5 Minutes",
          "Physical Penetration +1",
          "Casts [Pierced Wound] by 100% as many as hits made with normal ATK",
          "Every normal attack hit inflicts [Pierced Wound]. Skill attacks have 100% chance to change enemys [Pierced Wound] to [Enhanced Pierced Wound]"
        ]
      },
      {
        "level": "Level 10",
        "effects": [
          "Duration 5 Minutes",
          "Physical Penetration +10",
          "Casts [Pierced Wound] by 100% as many as hits made with normal ATK",
          "Every normal attack hit inflicts [Pierced Wound]. Skill attacks have 100% chance to change enemys [Pierced Wound] to [Enhanced Pierced Wound]"
        ]
      },
      {
        "level": "Level 11",
        "effects": [
          "Duration 5 Minutes",
          "Physical Penetration +11",
          "A.R. +1",
          "Casts [Pierced Wound] by 100% as many as hits made with normal ATK",
          "Every normal attack hit inflicts [Pierced Wound]. Skill attacks have 100% chance to change enemys [Pierced Wound] to [Enhanced Pierced Wound]"
        ]
      },
      {
        "level": "Level 12",
        "effects": [
          "Duration 5 Minutes",
          "Physical Penetration +12",
          "A.R. +1",
          "Casts [Pierced Wound] by 100% as many as hits made with normal ATK",
          "Every normal attack hit inflicts [Pierced Wound]. Skill attacks have 100% chance to change enemys [Pierced Wound] to [Enhanced Pierced Wound]"
        ]
      },
      {
        "level": "Level 13",
        "effects": [
          "Duration 5 Minutes",
          "Physical Penetration +13",
          "A.R. +1",
          "Casts [Pierced Wound] by 100% as many as hits made with normal ATK",
          "Every normal attack hit inflicts [Pierced Wound]. Skill attacks have 100% chance to change enemys [Pierced Wound] to [Enhanced Pierced Wound]"
        ]
      }
    ]
  },
  "stance_overview": [
    {
      "stance_name": "Bare Knuckle",
      "equipped_items": "None",
      "icon_position": {
        "x": -150,
        "y": 0
      }
    },
    {
      "stance_name": "Bloody Rose",
      "equipped_items": "Dagger",
      "icon_position": {
        "x": -100,
        "y": -200
      }
    }
  ],
  "stances": [
    {
      "name": "Bare Knuckle",
      "info": {
        "Targets": "1 enemy",
        "Range": "1m away",
        "Splash": "None",
        "Hits per attack": "2",
        "Hits flying": "No",
        "Flying": "No",
        "Regenerate SP": "Yes"
      },
      "stats": {
        "ASPD": "167",
        "Bonus ATK": "0%",
        "MSPD": "1",
        "MSPD Limit": "8.50",
        "ACC": "100",
        "EVA": "0",
        "BLK": "0",
        "Fire RES": "0",
        "Ice RES": "0",
        "Lightning RES": "0",
        "Abnormal RES": "0"
      },
      "lv25_bonus": {},
      "skills": [],
      "lv25_bonus_extra": [
        "None"
      ],
      "equipped_items": "None",
      "icon_position": {
        "x": -150,
        "y": 0
      }
    },
    {
      "name": "Bloody Rose",
      "info": {
        "Targets": "1 enemy",
        "Range": "1m away",
        "Splash": "None",
        "Hits per attack": "3",
        "Hits flying": "No",
        "Flying": "No",
        "Regenerate SP": "Yes",
        "Physical DMG": "-5%",
        "Shooting DMG": "-25%",
        "Magical DMG": "+15%"
      },
      "stats": {
        "ASPD": "210",
        "Bonus ATK": "300%",
        "MSPD": "1",
        "MSPD Limit": "8.50",
        "ACC": "100",
        "EVA": "0",
        "BLK": "0",
        "Fire RES": "0",
        "Ice RES": "0",
        "Lightning RES": "0",
        "Abnormal RES": "0"
      },
      "lv25_bonus": {
        "Evasion": "+25",
        "Critical": "+15",
        "Penetration": "10+20",
        "Immunity": "10+5"
      },
      "skills": [
        {
          "name": "Dagger Felt",
          "image": "blr_Daggerpelt.jpg",
          "description": "Throws a poisoned dagger to bring critical Debuff to the enemy.",
          "target": "1 adjacent enemy",
          "casting_time": "Instant",
          "cooldown": "5 sec.",
          "duration": "1.2 sec.",
          "hits_flying": "Yes",
          "knock_down": "Yes",
          "sp_cost": "150",
          "aggro": "60",
          "skill_type": "Melee",
          "levels": [
            {
              "level": "Level 1",
              "value": "АТК: 1500%"
            },
            {
              "level": "Level 10",
              "value": "АТК: 3000%"
            },
            {
              "level": "Level 11",
              "value": "АТК: 3300%"
            },
            {
              "level": "Level 12",
              "value": "АТК: 3600%"
            },
            {
              "level": "Level 13",
              "value": "АТК: 3600%"
            }
          ],
          "special": []
        },
        {
          "name": "Intrickage",
          "image": "blr_Intrinsic.jpg",
          "description": "Throws numbers of blades in a circle while rotating and then jumps.",
          "target": "Up to 8 enemies within a range of 8m",
          "casting_time": "Instant",
          "cooldown": "15 sec.",
          "duration": "2.533 sec.",
          "hits_flying": "Yes",
          "knock_down": "Yes",
          "sp_cost": "300",
          "aggro": "103",
          "skill_type": "Melee",
          "levels": [
            {
              "level": "Level 1",
              "value": "АТК: 900%"
            },
            {
              "level": "Level 10",
              "value": "АТК: 1800%"
            },
            {
              "level": "Level 11",
              "value": "АТК: 1980%"
            },
            {
              "level": "Level 12",
              "value": "АТК: 2160%"
            },
            {
              "level": "Level 13",
              "value": "АТК: 2160%"
            }
          ],
          "special": []
        },
        {
          "name": "Morande",
          "image": "blr_Morande.jpg",
          "description": "Stabs the enemy all over with a dagger.",
          "target": "1 adjacent enemy",
          "casting_time": "Instant",
          "cooldown": "20 sec.",
          "duration": "2.533 sec.",
          "hits_flying": "No",
          "knock_down": "Yes",
          "sp_cost": "600",
          "aggro": "150",
          "skill_type": "Melee",
          "levels": [
            {
              "level": "Level 1",
              "value": "АТК: 2500%"
            },
            {
              "level": "Level 10",
              "value": "АТК: 5000%"
            }
          ],
          "special": []
        },
        {
          "name": "Dodge",
          "image": "blr_Dodge.jpg",
          "description": "Raises the mind to the extremes to avoid enemys attacks.",
          "target": "",
          "casting_time": "Instant",
          "cooldown": "45 sec.",
          "duration": "1.03 sec.",
          "hits_flying": "No",
          "knock_down": "No",
          "sp_cost": "300",
          "aggro": "0",
          "skill_type": "Buff",
          "levels": [
            {
              "level": "Level 1",
              "value": "Duration 5 Minutes."
            },
            {
              "level": "Level 10",
              "value": "Duration 5 Minutes."
            },
            {
              "level": "Level 11",
              "value": "Duration 5 Minutes."
            },
            {
              "level": "Level 12",
              "value": "Duration 5 Minutes."
            },
            {
              "level": "Level 13",
              "value": "Duration 5 Minutes."
            }
          ],
          "special": []
        },
        {
          "name": "Cassina Kistlet",
          "image": "blr_CascinaCastlet.jpg",
          "description": "Resistance Heyran moves quickly to cut targets cruelly.",
          "target": "Up to 6 enemies 10m away and within a 1.8m width",
          "casting_time": "Instant",
          "cooldown": "20 sec.",
          "duration": "2.033 sec.",
          "hits_flying": "No",
          "knock_down": "Yes",
          "sp_cost": "400",
          "aggro": "80",
          "skill_type": "Melee",
          "levels": [
            {
              "level": "Level 1",
              "value": "АТК: 3000%"
            },
            {
              "level": "Level 10",
              "value": "АТК: 6000%"
            }
          ],
          "special": []
        }
      ],
      "lv25_bonus_extra": [
        "[RE: PvE] Skill DMG increases equal to 8% of extra [STR]",
        "[PVP/PVE Maps] Additional 3% DMG according to extra [STR]",
        "Ignore additional DEF according to extra [STR] * 3",
        "Additional DMG against [PC] + 1x",
        "Additional DMG against Monster according to 3 * 50"
      ],
      "equipped_items": "Dagger",
      "icon_position": {
        "x": -100,
        "y": -200
      }
    }
  ]
}