{
  "slug": "Sharon2",
  "equipment": {
    "category": "Usable Equipment",
    "medal": "Knight of Londinium Blooming Daisy",
    "head": "None",
    "earring": "Earring",
    "face": "None",
    "accessory": "Accessory",
    "necklace": "Necklace",
    "back": "All Characters",
    "armor": "Coat",
    "costume": "None",
    "gloves": "Gloves",
    "ring": "Ring",
    "weapon_costume": "Halloween Rod Costume Halloween Rod Costume (Event) Staff of Prophet Staff of Prophet (Event) Halloween Spirit Rod",
    "belt": "Belt",
    "shoes": "Shoes",
    "artifact": "Fragment of Cortes",
    "runestone": "Runestone",
    "pet_spirit": "Pet Spirit"
  },
  "character_buff": {
    "name": "Displayed",
    "image": "job_displayed.jpg",
    "description": "Engrave the power of the Ancient Crest to yourself.",
    "target": "Apply to yourself.",
    "casting_time": "0 sec.",
    "cooldown": "50 sec.",
    "duration": "1.7 sec.",
    "sp_cost": "320",
    "consume_item": "Ancient Star Orb × 10",
    "levels": [
      {
        "level": "Level 10",
        "effects": [
          "Duration : 5 Minutes",
          "A.R. +2",
          "Mental Penetration +15",
          "ATK +50%",
          "INT +15"
        ]
      }
    ]
  },
  "stance_overview": [
    {
      "stance_name": "Psychokinesis",
      "equipped_items": "None",
      "icon_position": {
        "x": -200,
        "y": -100
      }
    },
    {
      "stance_name": "Psychokinesis",
      "equipped_items": "Staff",
      "icon_position": {
        "x": -200,
        "y": -100
      }
    },
    {
      "stance_name": "Fate Sentence",
      "equipped_items": "Staff",
      "icon_position": {
        "x": -150,
        "y": 0
      }
    }
  ],
  "stances": [
    {
      "name": "Psychokinesis",
      "info": {
        "Targets": "1 enemy",
        "Range": "1~10m away",
        "Splash": "None",
        "Hits per attack": "1",
        "Hits flying": "Yes",
        "Flying": "No",
        "Regenerate SP": "Yes"
      },
      "stats": {
        "ASPD": "170",
        "Bonus ATK": "200%",
        "MSPD": "1",
        "MSPD Limit": "8.00",
        "ACC": "100",
        "EVA": "0",
        "BLK": "0",
        "Fire RES": "0",
        "Ice RES": "0",
        "Lightning RES": "0",
        "Abnormal RES": "0"
      },
      "lv25_bonus": {},
      "skills": [
        {
          "name": "Strike Back",
          "image": "psy_strikesback.jpg",
          "description": "Blows an enemy away with a powerful psychokinetic attack.",
          "target": "1 enemy within a range of 10m",
          "casting_time": "1.8 sec.",
          "cooldown": "0 sec.",
          "duration": "1.6 sec.",
          "hits_flying": "Yes",
          "knock_down": "Yes",
          "sp_cost": "60",
          "aggro": "84",
          "skill_type": "Magic",
          "levels": [
            {
              "level": "Level 1",
              "value": "АТК: 358%"
            },
            {
              "level": "Level 10",
              "value": "АТК: 716%"
            }
          ],
          "special": []
        },
        {
          "name": "Web",
          "image": "psy_web.jpg",
          "description": "Immobilize all enemies within range by pinning them to the ground.",
          "target": "Up to 6 enemies 5.5m away and within a 4m radius",
          "casting_time": "1 sec.",
          "cooldown": "15 sec.",
          "duration": "1.1 sec.",
          "hits_flying": "Yes",
          "knock_down": "No",
          "sp_cost": "120",
          "aggro": "0",
          "skill_type": "Buff",
          "levels": [
            {
              "level": "Level 1",
              "value": "80% chance to ["
            },
            {
              "level": "Level 10",
              "value": "80% chance to ["
            },
            {
              "level": "Level 11",
              "value": "80% chance to ["
            },
            {
              "level": "Level 12",
              "value": "80% chance to ["
            },
            {
              "level": "Level 13",
              "value": "80% chance to ["
            }
          ],
          "special": []
        },
        {
          "name": "Earthquake",
          "image": "psy_earthquake.jpg",
          "description": "Throws enemies violently into the air by creating a powerful earthquake.",
          "target": "",
          "casting_time": "1.633 sec.",
          "cooldown": "12 sec.",
          "duration": "1.67 sec.",
          "hits_flying": "No",
          "knock_down": "Yes",
          "sp_cost": "150",
          "aggro": "64",
          "skill_type": "Magic",
          "levels": [
            {
              "level": "Level 1",
              "value": "АТК: 216%"
            },
            {
              "level": "Level 10",
              "value": "АТК: 432%"
            }
          ],
          "special": []
        },
        {
          "name": "Apocalypse",
          "image": "psy_apocalypse.jpg",
          "description": "Concentrates all dark energy in the area into a powerful attack that consumes everything in its path.",
          "target": "",
          "casting_time": "2.633 sec.",
          "cooldown": "22.5 sec.",
          "duration": "1.63 sec.",
          "hits_flying": "Yes",
          "knock_down": "No",
          "sp_cost": "180",
          "aggro": "43",
          "skill_type": "Magic",
          "levels": [
            {
              "level": "Level 1",
              "value": "АТК: 157%"
            },
            {
              "level": "Level 10",
              "value": "АТК: 314%"
            },
            {
              "level": "Level 11",
              "value": "АТК: 345%"
            }
          ],
          "special": []
        }
      ],
      "lv25_bonus_extra": [
        "None"
      ],
      "equipped_items": "None",
      "icon_position": {
        "x": -200,
        "y": -100
      }
    },
    {
      "name": "Fate Sentence",
      "info": {
        "Targets": "3 enemies",
        "Range": "14m away",
        "Splash": "100% DMG within  2m range",
        "Hits per attack": "3",
        "Hits flying": "Yes",
        "Flying": "Yes",
        "Regenerate SP": "No",
        "Physical DMG": "-10%",
        "Shooting DMG": "+25%",
        "Magical DMG": "-10%",
        "Debuff RES": "-10%"
      },
      "stats": {
        "ASPD": "242",
        "Bonus ATK": "240%",
        "MSPD": "1",
        "MSPD Limit": "8.00",
        "ACC": "100",
        "EVA": "0",
        "BLK": "0",
        "Fire RES": "0",
        "Ice RES": "0",
        "Lightning RES": "0",
        "Abnormal RES": "0"
      },
      "lv25_bonus": {
        "Penetration": "10+25",
        "Immunity": "5+5"
      },
      "skills": [
        {
          "name": "Sailient",
          "image": "fat_saliant.jpg",
          "description": "Use the power of the Ancient Crest to damage the enemy with quick attacks.",
          "target": "",
          "casting_time": "Instant",
          "cooldown": "12 sec.",
          "duration": "1.833 sec.",
          "hits_flying": "No",
          "knock_down": "Yes",
          "sp_cost": "550",
          "aggro": "72",
          "skill_type": "Magic",
          "levels": [
            {
              "level": "Level 1",
              "value": "АТК: 1300%"
            },
            {
              "level": "Level 10",
              "value": "АТК: 2600%"
            }
          ],
          "special": []
        },
        {
          "name": "Volunt",
          "image": "fat_volant.jpg",
          "description": "Attack enemies by engraving the Ancient Crest onto the ground and blasting it away.",
          "target": "Up to 5 enemies within a range of 8m",
          "casting_time": "1.533 sec.",
          "cooldown": "14 sec.",
          "duration": "1.433 sec.",
          "hits_flying": "Yes",
          "knock_down": "Yes",
          "sp_cost": "440",
          "aggro": "49",
          "skill_type": "Magic",
          "levels": [
            {
              "level": "Level 1",
              "value": "АТК: 1500%"
            },
            {
              "level": "Level 10",
              "value": "АТК: 3000%"
            }
          ],
          "special": []
        },
        {
          "name": "Passant",
          "image": "fat_passant.jpg",
          "description": "Using the power of the Ancient Crest, create a gust of psychokinetic force to bring enemies to the center and confine them.",
          "target": "5 enemies within 3m - 12m, 5m radius",
          "casting_time": "1.466 sec.",
          "cooldown": "14 sec.",
          "duration": "2.133 sec.",
          "hits_flying": "Yes",
          "knock_down": "No",
          "sp_cost": "680",
          "aggro": "72",
          "skill_type": "Magic",
          "levels": [
            {
              "level": "Level 1",
              "value": "АТК: 1800%"
            },
            {
              "level": "Level 10",
              "value": "АТК: 3600%"
            }
          ],
          "special": []
        },
        {
          "name": "Rampunt Gardent",
          "image": "fat_rampantgardant.jpg",
          "description": "Use the power of the Ancient Crest to fire psychokinetic bullets at enemies continuously.",
          "target": "1 enemy within a range of 3m - 12m",
          "casting_time": "2.066 sec.",
          "cooldown": "12 sec.",
          "duration": "1.366 sec.",
          "hits_flying": "Yes",
          "knock_down": "Yes",
          "sp_cost": "760",
          "aggro": "245",
          "skill_type": "Magic",
          "levels": [
            {
              "level": "Level 1",
              "value": "АТК: 2200%"
            },
            {
              "level": "Level 10",
              "value": "АТК: 4400%"
            }
          ],
          "special": []
        },
        {
          "name": "Rampunt Regardent",
          "image": "fat_rampantregardant.jpg",
          "description": "Force a psychokinetic attack by retrieving an ancient crest engraved on an object.",
          "target": "1 enemy within a range of 3m - 12m",
          "casting_time": "1.033 sec.",
          "cooldown": "14 sec.",
          "duration": "2.1 sec.",
          "hits_flying": "Yes",
          "knock_down": "Yes",
          "sp_cost": "920",
          "aggro": "245",
          "skill_type": "Magic",
          "levels": [
            {
              "level": "Level 1",
              "value": "АТК: 2400%"
            },
            {
              "level": "Level 10",
              "value": "АТК: 4800%"
            }
          ],
          "special": []
        }
      ],
      "lv25_bonus_extra": [
        "[RE: PvE] Skill DMG increases equal to 8% of extra [INT]",
        "[PVP/PVE Maps] Additional 3% DMG according to extra [INT]",
        "Ignore additional DEF according to extra [INT] * 3",
        "Additional DMG against [PC] + 1x",
        "Additional DMG against Monster according to 3 * 50"
      ],
      "equipped_items": "Staff",
      "icon_position": {
        "x": -150,
        "y": 0
      }
    }
  ]
}